MANIFEST.in
README.md
README.rst
setup.py
pyNmonAnalyzer.egg-info/PKG-INFO
pyNmonAnalyzer.egg-info/SOURCES.txt
pyNmonAnalyzer.egg-info/dependency_links.txt
pyNmonAnalyzer.egg-info/entry_points.txt
pyNmonAnalyzer.egg-info/top_level.txt
src/__init__.py
src/interactiveReport.tpl.html
src/pyNmonAnalyzer.py
src/pyNmonParser.py
src/pyNmonPlotter.py
src/pyNmonReport.py
src/test.nmon