Metadata-Version: 1.0
Name: pyNmonAnalyzer
Version: 1.0.9
Summary: Python tool for reformatting and plotting/graphing NMON output
Home-page: https://github.com/madmaze/pynmonanalyzer
Author: Matthias Lee
Author-email: pynmonanalyzer@madmaze.net
License: GPLv3
Keywords: python nmon analyzer pynmonanalyzer interactive static report visualization
Platform: UNKNOWN
